GUI/__init__.py
GUI/displayA.py
GUI/displayB.py
GUI/get_start.py
GUI/main_gui.py
GUI/optimization.py
GUI/para_setting.py
GUI/pro_define.py
GUI/project.py
GUI/sensitivity_analysis.py
GUI/validation.py
GUI/worker.py
GUI/component/__init__.py
GUI/component/add_para_widget.py
GUI/component/add_pro_widget.py
GUI/component/banner_widget.py
GUI/component/button_group.py
GUI/component/check_box.py
GUI/component/checkable_combo_box.py
GUI/component/combox_.py
GUI/component/display_OP.py
GUI/component/display_SA.py
GUI/component/double_tree_widget.py
GUI/component/hyper_widget.py
GUI/component/info_bar.py
GUI/component/line_box.py
GUI/component/link_card.py
GUI/component/message_box.py
GUI/component/new_project.py
GUI/component/obj_table.py
GUI/component/op_widget.py
GUI/component/open_project.py
GUI/component/para_table.py
GUI/component/process_widget.py
GUI/component/progress_bar.py
GUI/component/sa_widget.py
GUI/component/table_widget_para.py
GUI/component/table_widget_pro.py
GUI/component/tree_widget.py
GUI/component/utility.py
GUI/component/validation_widget.py
GUI/data/__init__.py
GUI/picture/__init__.py
GUI/pyd/__init__.py
GUI/qss/__init__.py
swatuq/__init__.py
swatuq/swat_parameters.json
swatuq/swat_uq.py
swatuq/utility.cpython-36m-x86_64-linux-gnu.so
swatuq-1.0.6.dist-info/LICENSE
swatuq-1.0.6.dist-info/METADATA
swatuq-1.0.6.dist-info/WHEEL
swatuq-1.0.6.dist-info/top_level.txt
swatuq-1.0.6.dist-info/RECORD
